simtorch/__init__.py
simtorch/py.typed
simtorch/version.py
simtorch/model/__init__.py
simtorch/model/sim_model.py
simtorch/similarity/__init__.py
simtorch/similarity/base_similarity.py
simtorch/similarity/cka.py
simtorch/similarity/delta_cka.py
simtorch/similarity/procrustes.py
simtorch/similarity/utils.py
simtorch-0.2.1.dist-info/LICENSE
simtorch-0.2.1.dist-info/METADATA
simtorch-0.2.1.dist-info/WHEEL
simtorch-0.2.1.dist-info/top_level.txt
simtorch-0.2.1.dist-info/RECORD
